README.md
setup.py
cirqqulacs/__init__.py
cirqqulacs/qulacs_density_matrix_simulator.py
cirqqulacs/qulacs_simulator.py
cirqqulacs.egg-info/PKG-INFO
cirqqulacs.egg-info/SOURCES.txt
cirqqulacs.egg-info/dependency_links.txt
cirqqulacs.egg-info/top_level.txt
tests/cpu/__init__.py
tests/cpu/test_qulacs_simulator.py
tests/cpu/test_qulacs_simulator_density_matrix.py
tests/gpu/__init__.py
tests/gpu/test_qulacs_simulator.py