Metadata-Version: 1.0
Name: cirqqulacs
Version: 0.1.0
Summary: Fast quantum circuit simulator Qulacs as backend for Cirq
Home-page: http://www.qulacs.org
Author: QunaSys
Author-email: qulacs@qunasys.com
License: MIT
Platform: UNKNOWN
